{
  "variants": {
    "facing=north,lit=false": {
      "model": "photosynthesis:block/skillet"
    },
    "facing=north,lit=true": {
      "model": "photosynthesis:block/skillet_hot"
    },
    "facing=south,lit=false": {
      "model": "photosynthesis:block/skillet",
      "y": 180
    },
    "facing=south,lit=true": {
      "model": "photosynthesis:block/skillet_hot",
      "y": 180
    },
    "facing=west,lit=false": {
      "model": "photosynthesis:block/skillet",
      "y": 270
    },
    "facing=west,lit=true": {
      "model": "photosynthesis:block/skillet_hot",
      "y": 270
    },
    "facing=east,lit=false": {
      "model": "photosynthesis:block/skillet",
      "y": 90
    },
    "facing=east,lit=true": {
      "model": "photosynthesis:block/skillet_hot",
      "y": 90
    }
  }
}